qermod/__init__.py
qermod/protocols.py
qermod/serialization.py
qermod/types.py
qermod/noise/__init__.py
qermod/noise/abstract.py
qermod/noise/composite.py
qermod/noise/primitive.py
qermod/noise/utils.py
qermod-0.3.1.dist-info/METADATA
qermod-0.3.1.dist-info/WHEEL
qermod-0.3.1.dist-info/licenses/LICENSE
qermod-0.3.1.dist-info/RECORD
