Metadata-Version: 2.4
Name: qermod
Version: 0.3.1
Summary: A quantum library to define error models across Pasqal's backends.
Author-email: Charles Moussa <charles.moussa@pasqal.com>, Roland Guichard <roland.guichard@pasqal.com>
License: Apache 2.0
License-File: LICENSE
Classifier: License :: Other/Proprietary License
Classifier: Programming Language :: Python
Classifier: Programming Language :: Python :: 3
Classifier: Programming Language :: Python :: 3.9
Classifier: Programming Language :: Python :: 3.10
Classifier: Programming Language :: Python :: 3.11
Classifier: Programming Language :: Python :: 3.12
Classifier: Programming Language :: Python :: 3.13
Classifier: Programming Language :: Python :: Implementation :: CPython
Classifier: Programming Language :: Python :: Implementation :: PyPy
Requires-Python: >=3.8
Requires-Dist: eval-type-backport
Requires-Dist: ipykernel
Requires-Dist: pydantic
Requires-Dist: qadence
Requires-Dist: qadence-commons
Provides-Extra: dev
Requires-Dist: black; extra == 'dev'
Requires-Dist: flake8; extra == 'dev'
Requires-Dist: hypothesis; extra == 'dev'
Requires-Dist: mypy; extra == 'dev'
Requires-Dist: pre-commit; extra == 'dev'
Requires-Dist: pytest; extra == 'dev'
Requires-Dist: pytest-cov; extra == 'dev'
Requires-Dist: pytest-xdist; extra == 'dev'
Requires-Dist: ruff; extra == 'dev'
